ez_setup.py
setup.py
base62/__init__.py
base62/_version.py
base62/base62.py
base62/test/__init__.py
base62/test/test_base62.py
z_base_62.egg-info/PKG-INFO
z_base_62.egg-info/SOURCES.txt
z_base_62.egg-info/dependency_links.txt
z_base_62.egg-info/not-zip-safe
z_base_62.egg-info/requires.txt
z_base_62.egg-info/top_level.txt