Metadata-Version: 1.0
Name: z-base-62
Version: 1.0.5
Summary: Please switch to using this package under its new name -- zbase62 -- http://pypi.python.org/pypi/zbase62 .
Home-page: http://allmydata.org/trac/zbase62
Author: Zooko O'Whielacronx
Author-email: zooko@zooko.com
License: BSD
Platform: UNKNOWN
Classifier: Development Status :: 5 - Production/Stable
Classifier: Environment :: Console
Classifier: License :: OSI Approved :: BSD License
Classifier: License :: DFSG approved
Classifier: Intended Audience :: Developers
Classifier: Intended Audience :: End Users/Desktop
Classifier: Intended Audience :: System Administrators
Classifier: Operating System :: Microsoft
Classifier: Operating System :: Microsoft :: Windows
Classifier: Operating System :: Unix
Classifier: Operating System :: POSIX :: Linux
Classifier: Operating System :: POSIX
Classifier: Operating System :: MacOS :: MacOS X
Classifier: Operating System :: Microsoft :: Windows :: Windows NT/2000
Classifier: Operating System :: OS Independent
Classifier: Natural Language :: English
Classifier: Programming Language :: Python
Classifier: Topic :: Utilities
Classifier: Topic :: System :: Systems Administration
Classifier: Topic :: Software Development :: Libraries
